itweet/__init__.py
itweet/analyzer.py
itweet/classifier.py
itweet/classifier_v1.py
itweet/client.py
itweet/hometimeline.py
itweet/timeline.py
itweet/user.py
itweet/usertimeline.py
itweet-0.0.1.dist-info/LICENSE
itweet-0.0.1.dist-info/METADATA
itweet-0.0.1.dist-info/WHEEL
itweet-0.0.1.dist-info/top_level.txt
itweet-0.0.1.dist-info/RECORD
