Metadata-Version: 2.1
Name: itweet
Version: 0.0.1
Summary: innovata-tweet
Home-page: https://github.com/innovata/itweet
Author: innovata sambong
Author-email: iinnovata@gmail.com
License: UNKNOWN
Platform: UNKNOWN
Classifier: Programming Language :: Python :: 3
Classifier: License :: OSI Approved :: MIT License
Classifier: Operating System :: OS Independent
